armone/__init__.py
armone/armone.py
armone/cleaner.py
armone/encoder.py
armone/renamer.py
armone-0.0.4.dist-info/LICENSE
armone-0.0.4.dist-info/METADATA
armone-0.0.4.dist-info/WHEEL
armone-0.0.4.dist-info/entry_points.txt
armone-0.0.4.dist-info/top_level.txt
armone-0.0.4.dist-info/RECORD
