Metadata-Version: 2.1
Name: armone
Version: 0.0.4
Summary: A powerful command line tool to obfuscate python scripts effectively!
Author-email: Kanav Bhasin <kanbhasin@gmail.com>
Project-URL: Homepage, https://github.com/nixdonut/armone
Project-URL: Bug Tracker, https://github.com/nixdonut/armone/issues
Classifier: Programming Language :: Python :: 3
Classifier: License :: OSI Approved :: MIT License
Classifier: Operating System :: OS Independent
Requires-Python: >=3.7
License-File: LICENSE
